setup.cfg
setup.py
lint381/__init__.py
lint381/__main__.py
lint381/c.py
lint381/cpp.py
lint381/linter.py
lint381/tokenizer.py
lint381.egg-info/PKG-INFO
lint381.egg-info/SOURCES.txt
lint381.egg-info/dependency_links.txt
lint381.egg-info/entry_points.txt
lint381.egg-info/requires.txt
lint381.egg-info/top_level.txt
lint381/matcher/__init__.py
lint381/matcher/include.py
test/test_linter.py
test/test_main.py
test/test_matcher.py
test/test_tokenizer.py