Metadata-Version: 1.0
Name: lint381
Version: 1.3.4
Summary: C and C++ linter for EECS 381.
Home-page: https://github.com/arxanas/lint381
Author: Waleed Khan
Author-email: wkhan@umich.edu
License: UNKNOWN
Platform: UNKNOWN
